sensor_state_data/__init__.py
sensor_state_data/base/__init__.py
sensor_state_data/binary_sensor/__init__.py
sensor_state_data/binary_sensor/device_class.py
sensor_state_data/data.py
sensor_state_data/description.py
sensor_state_data/device.py
sensor_state_data/device_class.py
sensor_state_data/enum.py
sensor_state_data/library.py
sensor_state_data/py.typed
sensor_state_data/sensor/__init__.py
sensor_state_data/sensor/device_class.py
sensor_state_data/units.py
sensor_state_data/value.py
sensor_state_data-2.19.0.dist-info/LICENSE
sensor_state_data-2.19.0.dist-info/METADATA
sensor_state_data-2.19.0.dist-info/WHEEL
sensor_state_data-2.19.0.dist-info/RECORD
